Metadata-Version: 2.1
Name: datanonymizer
Version: 0.2
Summary: Anonymizer tool for datasets such CSV files
Home-page: http://github.com/fgmacedo/datanonymizer
Author: Fernando Macedo
Author-email: fgmacedo@gmail.com
License: MIT
Keywords: data anonymizer
Platform: UNKNOWN
Classifier: Development Status :: 4 - Beta
Classifier: Intended Audience :: Developers
Classifier: Intended Audience :: System Administrators
Classifier: License :: OSI Approved :: MIT License
Classifier: Natural Language :: English
Classifier: Programming Language :: Python :: 3
Classifier: Programming Language :: Python :: 3.7
Classifier: Programming Language :: Python :: 3.8
Classifier: Programming Language :: Python :: 3.9
Classifier: Topic :: Software Development :: Libraries
Classifier: Topic :: Security
Provides-Extra: mimesis
